deephy/__init__.py
deephy/deephy.py
deephy-0.5.3.dist-info/METADATA
deephy-0.5.3.dist-info/WHEEL
deephy-0.5.3.dist-info/top_level.txt
deephy-0.5.3.dist-info/RECORD
