Metadata-Version: 2.1
Name: deephy
Version: 0.5.3
Author-email: Matt Groth <mjgroth@mit.edu>
Project-URL: Homepage, https://github.com/mgroth0/deephy
Project-URL: Bug Tracker, https://github.com/mgroth0/deephy/issues
Requires-Dist: cbor2
Requires-Dist: numpy
Requires-Dist: torch
